{
  "dataset_id": "TMFD6_2026-03-24_l1",
  "source_type": "real",
  "source": "clickhouse_hft.market_data",
  "generator": "ch_batch_export",
  "schema_version": 1,
  "rows": 610036,
  "fields": [
    "bid_px",
    "ask_px",
    "bid_qty",
    "ask_qty",
    "mid_price",
    "spread_bps",
    "volume",
    "local_ts"
  ],
  "symbols": [
    "TMFD6"
  ],
  "date": "2026-03-24",
  "data_fingerprint": "17523e9c26bdbb14b627f0dea75c09a44fdb60713686c4bef0e05b7862321569",
  "data_ul": 5,
  "price_scale_applied": 1000000.0,
  "created_at": "2026-03-26T06:03:10.851275+00:00"
}